[
    {
        "averageWindSpeed": {
            "kph": 8,
            "mph": 5
        },
        "maxWindGustSpeed": {
            "kph": null,
            "mph": null
        },
        "temperature": {
            "c": 23,
            "f": 73
        },
        "time": {
            "offset": "-10:00",
            "timezone": "Pacific/Honolulu",
            "utc": "2021-04-29T16:00:00Z"
        },
        "windDirection": {
            "description": "Northerly",
            "direction": "N"
        }
    },
    {
        "averageWindSpeed": {
            "kph": 11,
            "mph": 7
        },
        "maxWindGustSpeed": {
            "kph": null,
            "mph": null
        },
        "temperature": {
            "c": 23,
            "f": 73
        },
        "time": {
            "offset": "-10:00",
            "timezone": "Pacific/Honolulu",
            "utc": "2021-04-29T17:00:00Z"
        },
        "windDirection": {
            "description": "Northerly",
            "direction": "N"
        }
    },
    {
        "averageWindSpeed": {
            "kph": 13,
            "mph": 8
        },
        "maxWindGustSpeed": {
            "kph": null,
            "mph": null
        },
        "temperature": {
            "c": 24,
            "f": 76
        },
        "time": {
            "offset": "-10:00",
            "timezone": "Pacific/Honolulu",
            "utc": "2021-04-29T18:00:00Z"
        },
        "windDirection": {
            "description": "East North Easterly",
            "direction": "ENE"
        }
    },
    {
        "averageWindSpeed": {
            "kph": 18,
            "mph": 11
        },
        "maxWindGustSpeed": {
            "kph": null,
            "mph": null
        },
        "temperature": {
            "c": 25,
            "f": 77
        },
        "time": {
            "offset": "-10:00",
            "timezone": "Pacific/Honolulu",
            "utc": "2021-04-29T19:00:00Z"
        },
        "windDirection": {
            "description": "North Easterly",
            "direction": "NE"
        }
    },
    {
        "averageWindSpeed": {
            "kph": 18,
            "mph": 11
        },
        "maxWindGustSpeed": {
            "kph": null,
            "mph": null
        },
        "temperature": {
            "c": 26,
            "f": 79
        },
        "time": {
            "offset": "-10:00",
            "timezone": "Pacific/Honolulu",
            "utc": "2021-04-29T20:00:00Z"
        },
        "windDirection": {
            "description": "North North Easterly",
            "direction": "NNE"
        }
    },
    {
        "averageWindSpeed": {
            "kph": 18,
            "mph": 11
        },
        "maxWindGustSpeed": {
            "kph": null,
            "mph": null
        },
        "temperature": {
            "c": 27,
            "f": 81
        },
        "time": {
            "offset": "-10:00",
            "timezone": "Pacific/Honolulu",
            "utc": "2021-04-29T21:00:00Z"
        },
        "windDirection": {
            "description": "North North Easterly",
            "direction": "NNE"
        }
    },
    {
        "averageWindSpeed": {
            "kph": 9,
            "mph": 6
        },
        "maxWindGustSpeed": {
            "kph": null,
            "mph": null
        },
        "temperature": {
            "c": 28,
            "f": 82
        },
        "time": {
            "offset": "-10:00",
            "timezone": "Pacific/Honolulu",
            "utc": "2021-04-29T22:00:00Z"
        },
        "windDirection": {
            "description": "Northerly",
            "direction": "N"
        }
    },
    {
        "averageWindSpeed": {
            "kph": 9,
            "mph": 6
        },
        "maxWindGustSpeed": {
            "kph": null,
            "mph": null
        },
        "temperature": {
            "c": 28,
            "f": 82
        },
        "time": {
            "offset": "-10:00",
            "timezone": "Pacific/Honolulu",
            "utc": "2021-04-29T23:00:00Z"
        },
        "windDirection": {
            "description": "North Easterly",
            "direction": "NE"
        }
    },
    {
        "averageWindSpeed": {
            "kph": 18,
            "mph": 11
        },
        "maxWindGustSpeed": {
            "kph": null,
            "mph": null
        },
        "temperature": {
            "c": 28,
            "f": 83
        },
        "time": {
            "offset": "-10:00",
            "timezone": "Pacific/Honolulu",
            "utc": "2021-04-30T00:00:00Z"
        },
        "windDirection": {
            "description": "North North Easterly",
            "direction": "NNE"
        }
    },
    {
        "averageWindSpeed": {
            "kph": 22,
            "mph": 14
        },
        "maxWindGustSpeed": {
            "kph": null,
            "mph": null
        },
        "temperature": {
            "c": 29,
            "f": 84
        },
        "time": {
            "offset": "-10:00",
            "timezone": "Pacific/Honolulu",
            "utc": "2021-04-30T01:00:00Z"
        },
        "windDirection": {
            "description": "North North Easterly",
            "direction": "NNE"
        }
    },
    {
        "averageWindSpeed": {
            "kph": 22,
            "mph": 14
        },
        "maxWindGustSpeed": {
            "kph": null,
            "mph": null
        },
        "temperature": {
            "c": 29,
            "f": 84
        },
        "time": {
            "offset": "-10:00",
            "timezone": "Pacific/Honolulu",
            "utc": "2021-04-30T02:00:00Z"
        },
        "windDirection": {
            "description": "North Easterly",
            "direction": "NE"
        }
    },
    {
        "averageWindSpeed": {
            "kph": 21,
            "mph": 13
        },
        "maxWindGustSpeed": {
            "kph": null,
            "mph": null
        },
        "temperature": {
            "c": 27,
            "f": 81
        },
        "time": {
            "offset": "-10:00",
            "timezone": "Pacific/Honolulu",
            "utc": "2021-04-30T03:00:00Z"
        },
        "windDirection": {
            "description": "North Easterly",
            "direction": "NE"
        }
    },
    {
        "averageWindSpeed": {
            "kph": 21,
            "mph": 13
        },
        "maxWindGustSpeed": {
            "kph": null,
            "mph": null
        },
        "temperature": {
            "c": 26,
            "f": 79
        },
        "time": {
            "offset": "-10:00",
            "timezone": "Pacific/Honolulu",
            "utc": "2021-04-30T04:00:00Z"
        },
        "windDirection": {
            "description": "North Easterly",
            "direction": "NE"
        }
    },
    {
        "averageWindSpeed": {
            "kph": 22,
            "mph": 14
        },
        "maxWindGustSpeed": {
            "kph": null,
            "mph": null
        },
        "temperature": {
            "c": 25,
            "f": 77
        },
        "time": {
            "offset": "-10:00",
            "timezone": "Pacific/Honolulu",
            "utc": "2021-04-30T05:00:00Z"
        },
        "windDirection": {
            "description": "North Easterly",
            "direction": "NE"
        }
    },
    {
        "averageWindSpeed": {
            "kph": 22,
            "mph": 14
        },
        "maxWindGustSpeed": {
            "kph": null,
            "mph": null
        },
        "temperature": {
            "c": 24,
            "f": 76
        },
        "time": {
            "offset": "-10:00",
            "timezone": "Pacific/Honolulu",
            "utc": "2021-04-30T06:00:00Z"
        },
        "windDirection": {
            "description": "North Easterly",
            "direction": "NE"
        }
    },
    {
        "averageWindSpeed": {
            "kph": 18,
            "mph": 11
        },
        "maxWindGustSpeed": {
            "kph": null,
            "mph": null
        },
        "temperature": {
            "c": 24,
            "f": 75
        },
        "time": {
            "offset": "-10:00",
            "timezone": "Pacific/Honolulu",
            "utc": "2021-04-30T07:00:00Z"
        },
        "windDirection": {
            "description": "East North Easterly",
            "direction": "ENE"
        }
    },
    {
        "averageWindSpeed": {
            "kph": 17,
            "mph": 10
        },
        "maxWindGustSpeed": {
            "kph": null,
            "mph": null
        },
        "temperature": {
            "c": 24,
            "f": 75
        },
        "time": {
            "offset": "-10:00",
            "timezone": "Pacific/Honolulu",
            "utc": "2021-04-30T08:00:00Z"
        },
        "windDirection": {
            "description": "North Easterly",
            "direction": "NE"
        }
    }
]